{"name":"build-javascript","namedChunkGroups":{"polyfill":{"name":"polyfill","assets":[{"name":"webpack-runtime-94274f5f88239dcfb67c.js","size":5221},{"name":"polyfill-2808265e25f42b70fc60.js","size":85842}],"filteredAssets":0,"assetsSize":91063,"filteredAuxiliaryAssets":2,"auxiliaryAssetsSize":228526},"app":{"name":"app","assets":[{"name":"webpack-runtime-94274f5f88239dcfb67c.js","size":5221},{"name":"framework-ca5375752a1629f589a8.js","size":128695},{"name":"app-8790f9b154d267db0d8b.js","size":85774}],"filteredAssets":0,"assetsSize":219690,"filteredAuxiliaryAssets":3,"auxiliaryAssetsSize":696207},"component---src-pages-404-js":{"name":"component---src-pages-404-js","assets":[{"name":"styles.d97e17fc8a89e09b97cf.css","size":121357},{"name":"commons-1b95b5dfed65dd5ee241.js","size":70758},{"name":"component---src-pages-404-js-248028c9212a5ce07194.js","size":1012}],"filteredAssets":0,"assetsSize":193127,"filteredAuxiliaryAssets":58,"auxiliaryAssetsSize":1722340},"component---src-templates-blog-index-js":{"name":"component---src-templates-blog-index-js","assets":[{"name":"styles.d97e17fc8a89e09b97cf.css","size":121357},{"name":"commons-1b95b5dfed65dd5ee241.js","size":70758},{"name":"component---src-templates-blog-index-js-6c75a1b84dd3b4604aba.js","size":6398}],"filteredAssets":0,"assetsSize":198513,"filteredAuxiliaryAssets":58,"auxiliaryAssetsSize":1734980},"component---src-templates-blog-post-js":{"name":"component---src-templates-blog-post-js","assets":[{"name":"styles.d97e17fc8a89e09b97cf.css","size":121357},{"name":"071290cb-fd75778b6bf8f65e9fef.js","size":229415},{"name":"commons-1b95b5dfed65dd5ee241.js","size":70758},{"name":"component---src-templates-blog-post-js-7dac89e8a82fa4223b8d.js","size":177455}],"filteredAssets":0,"assetsSize":598985,"filteredAuxiliaryAssets":59,"auxiliaryAssetsSize":3426448}},"assetsByChunkName":{"polyfill":["webpack-runtime-94274f5f88239dcfb67c.js","polyfill-2808265e25f42b70fc60.js"],"app":["webpack-runtime-94274f5f88239dcfb67c.js","framework-ca5375752a1629f589a8.js","app-8790f9b154d267db0d8b.js"],"component---src-pages-404-js":["styles.d97e17fc8a89e09b97cf.css","commons-1b95b5dfed65dd5ee241.js","component---src-pages-404-js-248028c9212a5ce07194.js"],"component---src-templates-blog-index-js":["styles.d97e17fc8a89e09b97cf.css","commons-1b95b5dfed65dd5ee241.js","component---src-templates-blog-index-js-6c75a1b84dd3b4604aba.js"],"component---src-templates-blog-post-js":["styles.d97e17fc8a89e09b97cf.css","071290cb-fd75778b6bf8f65e9fef.js","commons-1b95b5dfed65dd5ee241.js","component---src-templates-blog-post-js-7dac89e8a82fa4223b8d.js"]},"childAssetsByChunkName":{}}